azure/mgmt/logic/__init__.py
azure/mgmt/logic/logic_management_client.py
azure/mgmt/logic/version.py
azure/mgmt/logic/models/__init__.py
azure/mgmt/logic/models/access_key_regenerate_action_definition.py
azure/mgmt/logic/models/access_key_regenerate_action_definition_py3.py
azure/mgmt/logic/models/agreement_content.py
azure/mgmt/logic/models/agreement_content_py3.py
azure/mgmt/logic/models/artifact_content_properties_definition.py
azure/mgmt/logic/models/artifact_content_properties_definition_py3.py
azure/mgmt/logic/models/artifact_properties.py
azure/mgmt/logic/models/artifact_properties_py3.py
azure/mgmt/logic/models/as2_acknowledgement_connection_settings.py
azure/mgmt/logic/models/as2_acknowledgement_connection_settings_py3.py
azure/mgmt/logic/models/as2_agreement_content.py
azure/mgmt/logic/models/as2_agreement_content_py3.py
azure/mgmt/logic/models/as2_envelope_settings.py
azure/mgmt/logic/models/as2_envelope_settings_py3.py
azure/mgmt/logic/models/as2_error_settings.py
azure/mgmt/logic/models/as2_error_settings_py3.py
azure/mgmt/logic/models/as2_mdn_settings.py
azure/mgmt/logic/models/as2_mdn_settings_py3.py
azure/mgmt/logic/models/as2_message_connection_settings.py
azure/mgmt/logic/models/as2_message_connection_settings_py3.py
azure/mgmt/logic/models/as2_one_way_agreement.py
azure/mgmt/logic/models/as2_one_way_agreement_py3.py
azure/mgmt/logic/models/as2_protocol_settings.py
azure/mgmt/logic/models/as2_protocol_settings_py3.py
azure/mgmt/logic/models/as2_security_settings.py
azure/mgmt/logic/models/as2_security_settings_py3.py
azure/mgmt/logic/models/as2_validation_settings.py
azure/mgmt/logic/models/as2_validation_settings_py3.py
azure/mgmt/logic/models/assembly_definition.py
azure/mgmt/logic/models/assembly_definition_paged.py
azure/mgmt/logic/models/assembly_definition_py3.py
azure/mgmt/logic/models/assembly_properties.py
azure/mgmt/logic/models/assembly_properties_py3.py
azure_mgmt_logic-3.0.0.dist-info/METADATA
azure_mgmt_logic-3.0.0.dist-info/RECORD
azure_mgmt_logic-3.0.0.dist-info/WHEEL
azure_mgmt_logic-3.0.0.dist-info/top_level.txt
